docs/html/index.html
docs/html/search.js
docs/html/xrayclient/xray_client.html
docs/html/xrayclient.html
LICENSE
README.md
xrayclient/__init__.py
xrayclient/xray_client.py
xrayclient-0.1.9.dist-info/LICENSE
xrayclient-0.1.9.dist-info/METADATA
xrayclient-0.1.9.dist-info/WHEEL
xrayclient-0.1.9.dist-info/RECORD
