Metadata-Version: 2.1
Name: xrayclient
Version: 0.1.9
Summary: Python Client for Xray Test Management for Jira
Home-page: https://github.com/arusatech/xrayclient
License: MIT
Keywords: xray,jira,test-management,graphql,api-client
Author: AR USA LLC
Author-email: arusa@arusatech.com
Requires-Python: >=3.12,<3.14
Classifier: Development Status :: 4 - Beta
Classifier: Intended Audience :: Developers
Classifier: License :: OSI Approved :: MIT License
Classifier: Operating System :: OS Independent
Classifier: Programming Language :: Python :: 3
Classifier: Programming Language :: Python :: 3.12
Classifier: Programming Language :: Python :: 3.13
Classifier: Topic :: Software Development :: Libraries :: Python Modules
Classifier: Topic :: Software Development :: Testing
Requires-Dist: dotenv (>=0.9.9,<0.10.0)
Requires-Dist: jira (>=3.10.5,<4.0.0)
Requires-Dist: jsonpath-nz (>=1.0.6,<2.0.0)
Requires-Dist: pdoc (>=15.0.4,<16.0.0)
Requires-Dist: requests (>=2.31.0,<3.0.0)
Requires-Dist: spacy (>=3.8.7,<4.0.0)
Project-URL: Documentation, https://github.com/arusatech/xrayclient/tree/main/docs/html
Project-URL: Repository, https://github.com/arusatech/xrayclient
